{"_id":0,"gName":"[商城]惠普（HP） 光影精灵4 窄边框高端游戏本（15.6英寸,i5-8300H四核,8G/128G+1T,1050Ti-4G独显,W10）","sort":"笔记本","price":"6,499","addDate":1.551443418984e+12,"status":1,"images":"15279833M.jpg","describe":"爬取数据"}
{"_id":1,"gName":"[商城]惠普（HP） 绿色光影精灵 游戏本（15.6英寸,i7-8750H,8G/128G+1T,1050Ti-4G独显,W10）","sort":"笔记本","price":"7,149","addDate":1.55144341899e+12,"status":1,"images":"15279738M.jpg","describe":"爬取数据"}
{"_id":2,"gName":"联想（Lenovo） 【爆款特惠】读秒开机超薄笔记本 120S（14英寸,Intel N3350,4G/128G固态,W10）","sort":"笔记本","price":"2,898","addDate":1.551443418991e+12,"status":1,"images":"15222909-M.jpg","describe":"爬取数据"}
{"_id":3,"gName":"[商城]戴尔（DELL） Vostro 15-3562-R1228B（15.6英寸屏,Win10,2GB独显,256GB固态硬盘,8GB内存,N3450）","sort":"笔记本","price":"3,399","addDate":1.551443418991e+12,"status":1,"images":"15218915M.jpg","describe":"爬取数据"}
{"_id":4,"gName":"戴尔（DELL） 成就笔记本Vostro 14-5468-R1605（14英寸屏,4G内存256G固态硬盘,集显无光驱,Win10,i5-7200U）","sort":"笔记本","price":"5,299","addDate":1.551443418992e+12,"status":1,"images":"15177645M.jpg","describe":"爬取数据"}
{"_id":5,"gName":"[商城]惠普（HP） 小欧15G 大屏超低价笔记本（15.6英寸,Intel N4000,4G/500G,核显,W10）","sort":"笔记本","price":"2,699","addDate":1.551443418992e+12,"status":1,"images":"15279786M.jpg","describe":"爬取数据"}
{"_id":6,"gName":"[商城]惠普（HP） 【定制】星系列 X360 360度翻触控窄边框（14英寸,i3-8145,4G/128G+500G,核显,W10）","sort":"笔记本","price":"4,699","addDate":1.551443418993e+12,"status":1,"images":"15279784M.jpg","describe":"爬取数据"}
{"_id":7,"gName":"[商城]惠普（HP） 星系列 X360 360度翻触控窄边框（14英寸,i3-8145,4G/128G,核显,W10）","sort":"笔记本","price":"4,499","addDate":1.551443418993e+12,"status":1,"images":"15279783M.jpg","describe":"爬取数据"}
{"_id":8,"gName":"惠普（HP） 【定制】星系列 星15 四核窄边框超低价（15.6英寸,AMD R3四核,8G/128G+1T,核显,W10）","sort":"笔记本","price":"3,899","addDate":1.551443418994e+12,"status":1,"images":"15279782M.jpg","describe":"爬取数据"}
{"_id":9,"gName":"惠普（HP） 星系列 星15 四核窄边框超低价（15.6英寸,AMD R3四核,4G/1T,核显,W10）","sort":"笔记本","price":"3,399","addDate":1.551443418995e+12,"status":1,"images":"15279781M.jpg","describe":"爬取数据"}
{"_id":10,"gName":"惠普（HP） 【定制】星系列 星15 四核窄边框超低价（15.6英寸,AMD R3四核,4G/128G+1T,核显,W10）","sort":"笔记本","price":"3,549","addDate":1.551443418995e+12,"status":1,"images":"15279780M.jpg","describe":"爬取数据"}
{"_id":11,"gName":"[商城]惠普（HP） 【定制】星系列 星14 窄边框便携轻薄（14英寸,i5-8250四核,8G/128G+500G,核显,W10）","sort":"笔记本","price":"4,699","addDate":1.551443418996e+12,"status":1,"images":"15279779M.jpg","describe":"爬取数据"}
{"_id":12,"gName":"[商城]惠普（HP） 【定制】星系列 星15 窄边框独显本（15.6英寸,i5-8265四核,8G/128G+500G,2G独显,W10）","sort":"笔记本","price":"5,299","addDate":1.551443418996e+12,"status":1,"images":"15279778M.jpg","describe":"爬取数据"}
{"_id":13,"gName":"[商城]惠普（HP） 【定制】小欧14S 8代i5窄边框高颜值（14英寸,i5-8250四核,8G/500G+128G,2G独显,W10）","sort":"笔记本","price":"4,499","addDate":1.551443418997e+12,"status":1,"images":"15279775M.jpg","describe":"爬取数据"}
{"_id":14,"gName":"[商城]惠普（HP） 【定制】小欧14S 8代i5窄边框高颜值（14英寸,i5-8250四核,4G/500G+128G,2G独显,W10）","sort":"笔记本","price":"4,499","addDate":1.551443418997e+12,"status":1,"images":"15279773M.jpg","describe":"爬取数据"}
{"_id":15,"gName":"[商城]惠普（HP） 小欧14S 8代i5窄边框高颜值（14英寸,i5-8250四核,4G/500G,2G独显,W10）","sort":"笔记本","price":"4,299","addDate":1.551443418998e+12,"status":1,"images":"15279772M.jpg","describe":"爬取数据"}
{"_id":16,"gName":"[商城]惠普（HP） 小欧14S 高速开机窄边框本（14英寸,Intel N4000,4G/128G固态,核显,W10）","sort":"笔记本","price":"2,999","addDate":1.551443418999e+12,"status":1,"images":"15279771M.jpg","describe":"爬取数据"}
{"_id":17,"gName":"[商城]惠普（HP） 小欧14S 窄边框超低价便携本（14英寸,Intel N4000,4G/500G,核显,W10,银色）","sort":"笔记本","price":"2,899","addDate":1.551443418999e+12,"status":1,"images":"15279770M.jpg","describe":"爬取数据"}
{"_id":18,"gName":"[商城]惠普（HP） 星系列 星14 窄边框便携超高配（14英寸,i7-8565四核,8G/128G+1T,2G独显,W10）","sort":"笔记本","price":"6,649","addDate":1.551443419e+12,"status":1,"images":"15279748M.jpg","describe":"爬取数据"}
{"_id":19,"gName":"[商城]惠普（HP） 星系列 星14 窄边框便携轻薄（14英寸,i5-8265四核,8G/256G固态,核显,W10）","sort":"笔记本","price":"5,249","addDate":1.551443419001e+12,"status":1,"images":"15279747M.jpg","describe":"爬取数据"}
{"_id":20,"gName":"宝马 BMW 530Le 新春版","sort":"汽车","price":"505,800","addDate":1.551451118415e+12,"status":1,"images":"15279854-M.jpg","describe":"爬取数据"}
{"_id":21,"gName":"凯迪拉克 ATS-L 东方尊享版","sort":"汽车","price":"309,900","addDate":1.551451118421e+12,"status":1,"images":"15279528-M.jpg","describe":"爬取数据"}
{"_id":22,"gName":"路虎 发现神行 240P SE","sort":"汽车","price":"404,800","addDate":1.551451118423e+12,"status":1,"images":"15279527-M.jpg","describe":"爬取数据"}
{"_id":23,"gName":"上汽大众 帕萨特 PHEV 混动精英版","sort":"汽车","price":"249,900","addDate":1.551451118424e+12,"status":1,"images":"15278849-M.jpg","describe":"爬取数据"}
{"_id":24,"gName":"荣威 eRX5 LED尊贵版","sort":"汽车","price":"269,900","addDate":1.551451118428e+12,"status":1,"images":"15277036-M.jpg","describe":"爬取数据"}
{"_id":25,"gName":"上汽大众 途观L 280TSI 新春版","sort":"汽车","price":"236,800","addDate":1.551451118429e+12,"status":1,"images":"15277035-M.jpg","describe":"爬取数据"}
{"_id":26,"gName":"沃尔沃 XC60 T5 智逸版","sort":"汽车","price":"399,900","addDate":1.55145111843e+12,"status":1,"images":"15275168-M.jpg","describe":"爬取数据"}
{"_id":27,"gName":"英菲尼迪 Q50L 舒适版","sort":"汽车","price":"269,800","addDate":1.551451118431e+12,"status":1,"images":"15275166-M.jpg","describe":"爬取数据"}
{"_id":28,"gName":"荣威 eRX5 LED尊贵版","sort":"汽车","price":"213,100","addDate":1.551451118432e+12,"status":1,"images":"15274362M.jpg","describe":"爬取数据"}
{"_id":29,"gName":"荣威 ei6 智享版","sort":"汽车","price":"165,800","addDate":1.551451118432e+12,"status":1,"images":"15274358M.jpg","describe":"爬取数据"}
{"_id":30,"gName":"路虎 揽胜运动 插电式混合动力车 P400e","sort":"汽车","price":"908,000","addDate":1.551451118433e+12,"status":1,"images":"15274353M.jpg","describe":"爬取数据"}
{"_id":31,"gName":"路虎 揽胜运动 插电式混合动力车 P400e","sort":"汽车","price":"908,000","addDate":1.551451118434e+12,"status":1,"images":"15267015-M.jpg","describe":"爬取数据"}
{"_id":33,"gName":"卡西欧（CASIO）  指针系列经典时尚商务简约防水男表 MTP-1303D系列","sort":"钟表","price":"329","addDate":1.551451264553e+12,"status":1,"images":"15240457M.jpg","describe":"爬取数据"}
{"_id":34,"gName":"卡西欧（CASIO）  指针系列经典时尚商务简约防水男表 MTP-1303L-7B","sort":"钟表","price":"329","addDate":1.551451264559e+12,"status":1,"images":"15240455M.jpg","describe":"爬取数据"}
{"_id":35,"gName":"[商城]斯沃琪（SWATCH） 原创系列 男女石英表GW186","sort":"钟表","price":"432","addDate":1.551451264562e+12,"status":1,"images":"15249858M.jpg","describe":"爬取数据"}
{"_id":36,"gName":"斯沃琪（SWATCH） 原创炫彩系列石英男表SUOB401","sort":"钟表","price":"459","addDate":1.551451264563e+12,"status":1,"images":"15243645M.jpg","describe":"爬取数据"}
{"_id":37,"gName":"卡西欧（CASIO） 商务双日历石英男表时尚腕表 MTP-1374D-1A","sort":"钟表","price":"459","addDate":1.551451264564e+12,"status":1,"images":"15207253M.jpg","describe":"爬取数据"}
{"_id":38,"gName":"卡西欧（CASIO） 男士运动防水夜光石英腕表 MTP-1374D-7A","sort":"钟表","price":"469","addDate":1.551451264566e+12,"status":1,"images":"15167030M.jpg","describe":"爬取数据"}
{"_id":39,"gName":"[商城]斯沃琪（SWATCH） 原创系列 男女石英表SUOB724","sort":"钟表","price":"495","addDate":1.551451264568e+12,"status":1,"images":"15189138M.jpg","describe":"爬取数据"}
{"_id":40,"gName":"[商城]斯沃琪（SWATCH） 原创系列 男女石英表 SUON700","sort":"钟表","price":"495","addDate":1.551451264569e+12,"status":1,"images":"15189136M.jpg","describe":"爬取数据"}
{"_id":41,"gName":"[商城]斯沃琪（SWATCH） 原创系列 男女石英表 SUOB720","sort":"钟表","price":"495","addDate":1.55145126457e+12,"status":1,"images":"15189135M.jpg","describe":"爬取数据"}
{"_id":42,"gName":"[商城]斯沃琪（SWATCH） 原创系列 男女石英表 SUOB704","sort":"钟表","price":"495","addDate":1.551451264571e+12,"status":1,"images":"15189134M.jpg","describe":"爬取数据"}
{"_id":43,"gName":"斯沃琪（SWATCH） 原创炫彩系列石英男表SUOW701","sort":"钟表","price":"498","addDate":1.551451264572e+12,"status":1,"images":"15243928M.jpg","describe":"爬取数据"}
{"_id":44,"gName":"斯沃琪（SWATCH） 原创炫彩系列石英男表SUOB714","sort":"钟表","price":"498","addDate":1.551451264574e+12,"status":1,"images":"15243922M.jpg","describe":"爬取数据"}
{"_id":45,"gName":"斯沃琪（SWATCH） 原创透视系列石英男表SUOW129","sort":"钟表","price":"518","addDate":1.551451264575e+12,"status":1,"images":"15243927M.jpg","describe":"爬取数据"}
{"_id":46,"gName":"斯沃琪（SWATCH） 原创透视系列石英男表SUOW100","sort":"钟表","price":"518","addDate":1.551451264576e+12,"status":1,"images":"15243926M.jpg","describe":"爬取数据"}
{"_id":47,"gName":"卡西欧（CASIO） G-SHOCK系列手表 防水防震 荧光照明 闹钟日历 运动潮流时尚男表 DW-5600HR-1","sort":"钟表","price":"690","addDate":1.551451264577e+12,"status":1,"images":"15239061M.jpg","describe":"爬取数据"}
{"_id":48,"gName":"卡西欧（CASIO） 大众指针系列 大表盘三眼 防水休闲男表 BEM-506GL-1A","sort":"钟表","price":"699","addDate":1.551451264578e+12,"status":1,"images":"15265542M.jpg","describe":"爬取数据"}
{"_id":49,"gName":"卡西欧（CASIO） 大众指针系列 大表盘三眼 防水休闲男表 BEM-506CL-1A","sort":"钟表","price":"699","addDate":1.551451264579e+12,"status":1,"images":"15265541M.jpg","describe":"爬取数据"}
